ipydingo/__init__.py
ipydingo/_version.py
ipydingo/video_session.py
ipydingo/labextension/package.json
ipydingo/labextension/static/261.3d73756fbe9a09582bbc.js
ipydingo/labextension/static/434.fb3b92829dcedafc4b0c.js
ipydingo/labextension/static/621.aae5f0a57e6e809e7947.js
ipydingo/labextension/static/621.aae5f0a57e6e809e7947.js.LICENSE.txt
ipydingo/labextension/static/remoteEntry.c352f8c3645489905063.js
ipydingo/labextension/static/style.js
ipydingo/nbextension/extension.js
ipydingo/nbextension/index.js
ipydingo/nbextension/index.js.LICENSE.txt
ipydingo-0.1.0a0.data/data/etc/jupyter/nbconfig/notebook.d/ipydingo.json
ipydingo-0.1.0a0.data/data/share/jupyter/labextensions/ipydingo/install.json
ipydingo-0.1.0a0.data/data/share/jupyter/labextensions/ipydingo/package.json
ipydingo-0.1.0a0.data/data/share/jupyter/labextensions/ipydingo/static/261.3d73756fbe9a09582bbc.js
ipydingo-0.1.0a0.data/data/share/jupyter/labextensions/ipydingo/static/434.fb3b92829dcedafc4b0c.js
ipydingo-0.1.0a0.data/data/share/jupyter/labextensions/ipydingo/static/621.aae5f0a57e6e809e7947.js
ipydingo-0.1.0a0.data/data/share/jupyter/labextensions/ipydingo/static/621.aae5f0a57e6e809e7947.js.LICENSE.txt
ipydingo-0.1.0a0.data/data/share/jupyter/labextensions/ipydingo/static/remoteEntry.c352f8c3645489905063.js
ipydingo-0.1.0a0.data/data/share/jupyter/labextensions/ipydingo/static/style.js
ipydingo-0.1.0a0.data/data/share/jupyter/nbextensions/ipydingo/extension.js
ipydingo-0.1.0a0.data/data/share/jupyter/nbextensions/ipydingo/index.js
ipydingo-0.1.0a0.data/data/share/jupyter/nbextensions/ipydingo/index.js.LICENSE.txt
ipydingo-0.1.0a0.dist-info/METADATA
ipydingo-0.1.0a0.dist-info/WHEEL
ipydingo-0.1.0a0.dist-info/top_level.txt
ipydingo-0.1.0a0.dist-info/RECORD
